ogarantia_streamlit_card/__init__.py
ogarantia_streamlit_card/frontend/build/asset-manifest.json
ogarantia_streamlit_card/frontend/build/bootstrap.min.css
ogarantia_streamlit_card/frontend/build/bootstrap.min.css.map
ogarantia_streamlit_card/frontend/build/index.html
ogarantia_streamlit_card/frontend/build/precache-manifest.71d4704b12d9470ef28318c05dc865f0.js
ogarantia_streamlit_card/frontend/build/service-worker.js
ogarantia_streamlit_card/frontend/build/static/js/2.8229b76d.chunk.js
ogarantia_streamlit_card/frontend/build/static/js/2.8229b76d.chunk.js.map
ogarantia_streamlit_card/frontend/build/static/js/main.3864f6db.chunk.js
ogarantia_streamlit_card/frontend/build/static/js/main.3864f6db.chunk.js.map
ogarantia_streamlit_card/frontend/build/static/js/runtime~main.d653cc00.js
ogarantia_streamlit_card/frontend/build/static/js/runtime~main.d653cc00.js.map
ogarantia_streamlit_card-0.0.2.dist-info/LICENSE
ogarantia_streamlit_card-0.0.2.dist-info/METADATA
ogarantia_streamlit_card-0.0.2.dist-info/WHEEL
ogarantia_streamlit_card-0.0.2.dist-info/top_level.txt
ogarantia_streamlit_card-0.0.2.dist-info/RECORD
