Metadata-Version: 2.1
Name: ogarantia-streamlit-card
Version: 0.0.2
Summary: A streamlit component to make UI cards, adapted for Ogarantia applications from `streamlit-card` by gamcoh (cohengamliel8@gmail.com)
Home-page: https://github.com/Ogarantia/st-card.git
Author: Wilder Lopes
Author-email: wilder@ogarantia.com
Keywords: card streamlit streamlit-component
Classifier: Programming Language :: Python :: 3
Classifier: Operating System :: OS Independent
Requires-Python: >=3.8
License-File: LICENSE
Requires-Dist: streamlit (>=0.63)
